DisplayInfo.py
KickAI.py
Main_Capture.py
Main_Collector.py
Main_FDG.py
Main_PyAIvsPyAI.py
Main_SinglePyAI.py
Main_SoundAI.py
TestSoundAI.py
pyftg/__init__.py
pyftg/aiinterface/ai_interface.py
pyftg/aiinterface/command_center.py
pyftg/aiinterface/soundgenai_interface.py
pyftg/grpc/asyncio/ai_controller.py
pyftg/grpc/asyncio/gateway.py
pyftg/grpc/threading/ai_controller.py
pyftg/grpc/threading/gateway.py
pyftg/grpc/threading/observer_gateway.py
pyftg/grpc/threading/observer_handler.py
pyftg/interfaces/async_gateway.py
pyftg/models/attack_data.py
pyftg/models/audio_data.py
pyftg/models/base_model.py
pyftg/models/character_data.py
pyftg/models/fft_data.py
pyftg/models/frame_data.py
pyftg/models/game_data.py
pyftg/models/hit_area.py
pyftg/models/key.py
pyftg/models/round_result.py
pyftg/models/screen_data.py
pyftg/models/enums/__init__.py
pyftg/models/enums/action.py
pyftg/models/enums/data_flag.py
pyftg/models/enums/flag.py
pyftg/models/enums/int_action.py
pyftg/models/enums/int_state.py
pyftg/models/enums/state.py
pyftg/models/enums/status_code.py
pyftg/protoc/__init__.py
pyftg/protoc/__init__.pyi
pyftg/protoc/enum_pb2.py
pyftg/protoc/enum_pb2_grpc.py
pyftg/protoc/message_pb2.py
pyftg/protoc/message_pb2_grpc.py
pyftg/protoc/service_pb2.py
pyftg/protoc/service_pb2_grpc.py
pyftg/socket/asyncio/ai_controller.py
pyftg/socket/asyncio/gateway.py
pyftg/socket/asyncio/generative_sound_gateway.py
pyftg/socket/threading/ai_controller.py
pyftg/socket/threading/gateway.py
pyftg/socket/utils/asyncio.py
pyftg/socket/utils/threading.py
pyftg/utils/gateway.py
pyftg/utils/logging.py
pyftg/utils/protobuf.py
pyftg/utils/resource_loader.py
pyftg-2.1.1.dist-info/LICENSE
pyftg-2.1.1.dist-info/METADATA
pyftg-2.1.1.dist-info/WHEEL
pyftg-2.1.1.dist-info/top_level.txt
pyftg-2.1.1.dist-info/RECORD
