Metadata-Version: 2.1
Name: pyftg
Version: 2.1.1
Summary: An interface for implementing python AI in DareFightingICE
Author: TeamFightingICE
Project-URL: Homepage, https://github.com/TeamFightingICE/pyftg
Project-URL: Issues, https://github.com/TeamFightingICE/pyftg/issues
Classifier: Programming Language :: Python :: 3
Classifier: License :: OSI Approved :: MIT License
Classifier: Operating System :: OS Independent
Requires-Python: >=3.10
License-File: LICENSE
Requires-Dist: grpcio ~=1.62.1
Requires-Dist: grpcio-tools ~=1.62.1
Requires-Dist: protobuf ~=4.25.3
